README.rst
setup.py
flac2mp3/__init__.py
flac2mp3/convert_id3v2_to_utf8.py
flac2mp3.egg-info/PKG-INFO
flac2mp3.egg-info/SOURCES.txt
flac2mp3.egg-info/dependency_links.txt
flac2mp3.egg-info/entry_points.txt
flac2mp3.egg-info/not-zip-safe
flac2mp3.egg-info/requires.txt
flac2mp3.egg-info/top_level.txt