Metadata-Version: 2.1
Name: flac2mp3
Version: 0.6
Summary: Python flac2mp3 transcoding script
Home-page: https://github.com/bamthomas/flac2mp3
Author: Bruno Thomas
Author-email: bruno@barreverte.fr
License: MIT
Keywords: transcoding mp3 lame flac
Platform: UNKNOWN
Classifier: Programming Language :: Python
Classifier: Programming Language :: Python :: 3.6
Classifier: Programming Language :: Python :: 3.7
Classifier: Programming Language :: Python :: 3.8
Provides-Extra: dev
